Compiled from "ToChange.java"
public class edu.syr.pcpratts.studio.code.sootexample.tochange.ToChange extends java.lang.Object
  SourceFile: "ToChange.java"
  minor version: 0
  major version: 46
  Constant pool:
const #1 = Asciz	ToChange.java;
const #2 = Asciz	()Ljava/lang/String;;
const #3 = Asciz	()V;
const #4 = Asciz	main;
const #5 = NameAndType	#15:#2;//  run:()Ljava/lang/String;
const #6 = Asciz	hello world;
const #7 = Asciz	java/lang/Object;
const #8 = Asciz	edu/syr/pcpratts/studio/code/sootexample/tochange/ToChange;
const #9 = class	#7;	//  java/lang/Object
const #10 = Method	#22.#31;	//  java/io/PrintStream.println:(Ljava/lang/String;)V
const #11 = Asciz	java/lang/System;
const #12 = class	#11;	//  java/lang/System
const #13 = Asciz	save;
const #14 = NameAndType	#32:#33;//  m_str:Ljava/lang/String;
const #15 = Asciz	run;
const #16 = Method	#26.#5;	//  edu/syr/pcpratts/studio/code/sootexample/tochange/ToChange.run:()Ljava/lang/String;
const #17 = String	#6;	//  hello world
const #18 = Method	#26.#21;	//  edu/syr/pcpratts/studio/code/sootexample/tochange/ToChange.save:(Ljava/lang/String;)V
const #19 = Asciz	([Ljava/lang/String;)V;
const #20 = NameAndType	#25:#3;//  "<init>":()V
const #21 = NameAndType	#13:#36;//  save:(Ljava/lang/String;)V
const #22 = class	#38;	//  java/io/PrintStream
const #23 = Asciz	SourceFile;
const #24 = Asciz	println;
const #25 = Asciz	<init>;
const #26 = class	#8;	//  edu/syr/pcpratts/studio/code/sootexample/tochange/ToChange
const #27 = NameAndType	#28:#39;//  out:Ljava/io/PrintStream;
const #28 = Asciz	out;
const #29 = Method	#26.#20;	//  edu/syr/pcpratts/studio/code/sootexample/tochange/ToChange."<init>":()V
const #30 = Method	#9.#20;	//  java/lang/Object."<init>":()V
const #31 = NameAndType	#24:#36;//  println:(Ljava/lang/String;)V
const #32 = Asciz	m_str;
const #33 = Asciz	Ljava/lang/String;;
const #34 = Field	#26.#14;	//  edu/syr/pcpratts/studio/code/sootexample/tochange/ToChange.m_str:Ljava/lang/String;
const #35 = Field	#12.#27;	//  java/lang/System.out:Ljava/io/PrintStream;
const #36 = Asciz	(Ljava/lang/String;)V;
const #37 = Asciz	Code;
const #38 = Asciz	java/io/PrintStream;
const #39 = Asciz	Ljava/io/PrintStream;;

{
public edu.syr.pcpratts.studio.code.sootexample.tochange.ToChange();
  Code:
   Stack=1, Locals=1, Args_size=1
   0:	aload_0
   1:	invokespecial	#30; //Method java/lang/Object."<init>":()V
   4:	return

public static void main(java.lang.String[]);
  Code:
   Stack=3, Locals=1, Args_size=1
   0:	new	#26; //class edu/syr/pcpratts/studio/code/sootexample/tochange/ToChange
   3:	dup
   4:	invokespecial	#29; //Method "<init>":()V
   7:	dup
   8:	invokespecial	#16; //Method run:()Ljava/lang/String;
   11:	astore_0
   12:	getstatic	#35; //Field java/lang/System.out:Ljava/io/PrintStream;
   15:	aload_0
   16:	invokevirtual	#10; //Method java/io/PrintStream.println:(Ljava/lang/String;)V
   19:	aload_0
   20:	invokespecial	#18; //Method save:(Ljava/lang/String;)V
   23:	return

}

